{
  "zones": [
    {
      "domains": "1442976",
      "zone": "se"
    },
    {
      "domains": "465386",
      "zone": "tn"
    },
    {
      "domains": "159360",
      "zone": "kz"
    },
    {
      "domains": "77156",
      "zone": "lol"
    },
    {
      "domains": "49402",
      "zone": "lk"
    },
    {
      "domains": "38352",
      "zone": "pics"
    },
    {
      "domains": "28816",
      "zone": "mom"
    },
    {
      "domains": "13499",
      "zone": "dz"
    },
    {
      "domains": "12662",
      "zone": "ci"
    },
    {
      "domains": "11959",
      "zone": "gdn"
    },
    {
      "domains": "11055",
      "zone": "kg"
    },
    {
      "domains": "8414",
      "zone": "cy"
    },
    {
      "domains": "5151",
      "zone": "ruhr"
    },
    {
      "domains": "4762",
      "zone": "audio"
    },
    {
      "domains": "4170",
      "zone": "ax"
    },
    {
      "domains": "4143",
      "zone": "game"
    },
    {
      "domains": "2778",
      "zone": "hosting"
    },
    {
      "domains": "2083",
      "zone": "pr"
    },
    {
      "domains": "1995",
      "zone": "christmas"
    },
    {
      "domains": "1349",
      "zone": "br"
    },
    {
      "domains": "1238",
      "zone": "diet"
    },
    {
      "domains": "1194",
      "zone": "bt"
    },
    {
      "domains": "1112",
      "zone": "tz"
    },
    {
      "domains": "1048",
      "zone": "flowers"
    },
    {
      "domains": "727",
      "zone": "guitars"
    },
    {
      "domains": "559",
      "zone": "gn"
    },
    {
      "domains": "485",
      "zone": "auto"
    },
    {
      "domains": "481",
      "zone": "lr"
    },
    {
      "domains": "465",
      "zone": "xn--80ao21a"
    },
    {
      "domains": "336",
      "zone": "car"
    },
    {
      "domains": "295",
      "zone": "cars"
    },
    {
      "domains": "149",
      "zone": "xn--l1acc"
    },
    {
      "domains": "47",
      "zone": "ve"
    },
    {
      "domains": "23",
      "zone": "arpa"
    },
    {
      "domains": "5",
      "zone": "lb"
    }
  ],
  "total": "2353632"
}
