{
  "zones": [
    {
      "domains": "1442976",
      "zone": "se"
    },
    {
      "domains": "465386",
      "zone": "tn"
    },
    {
      "domains": "159360",
      "zone": "kz"
    },
    {
      "domains": "70325",
      "zone": "lol"
    },
    {
      "domains": "49579",
      "zone": "lk"
    },
    {
      "domains": "34915",
      "zone": "pics"
    },
    {
      "domains": "24775",
      "zone": "mom"
    },
    {
      "domains": "13408",
      "zone": "dz"
    },
    {
      "domains": "12687",
      "zone": "ci"
    },
    {
      "domains": "11977",
      "zone": "gdn"
    },
    {
      "domains": "11036",
      "zone": "kg"
    },
    {
      "domains": "8270",
      "zone": "cy"
    },
    {
      "domains": "5218",
      "zone": "ruhr"
    },
    {
      "domains": "4762",
      "zone": "audio"
    },
    {
      "domains": "4153",
      "zone": "ax"
    },
    {
      "domains": "4143",
      "zone": "game"
    },
    {
      "domains": "2792",
      "zone": "hosting"
    },
    {
      "domains": "2095",
      "zone": "pr"
    },
    {
      "domains": "1998",
      "zone": "christmas"
    },
    {
      "domains": "1349",
      "zone": "br"
    },
    {
      "domains": "1243",
      "zone": "diet"
    },
    {
      "domains": "1187",
      "zone": "bt"
    },
    {
      "domains": "1083",
      "zone": "tz"
    },
    {
      "domains": "1057",
      "zone": "flowers"
    },
    {
      "domains": "729",
      "zone": "guitars"
    },
    {
      "domains": "554",
      "zone": "gn"
    },
    {
      "domains": "491",
      "zone": "auto"
    },
    {
      "domains": "481",
      "zone": "lr"
    },
    {
      "domains": "465",
      "zone": "xn--80ao21a"
    },
    {
      "domains": "329",
      "zone": "car"
    },
    {
      "domains": "297",
      "zone": "cars"
    },
    {
      "domains": "150",
      "zone": "xn--l1acc"
    },
    {
      "domains": "46",
      "zone": "ve"
    },
    {
      "domains": "23",
      "zone": "arpa"
    },
    {
      "domains": "5",
      "zone": "lb"
    }
  ],
  "total": "2339344"
}
