{
  "zones": [
    {
      "domains": "2528344",
      "zone": "ch"
    },
    {
      "domains": "1414923",
      "zone": "se"
    },
    {
      "domains": "214544",
      "zone": "lol"
    },
    {
      "domains": "170875",
      "zone": "kz"
    },
    {
      "domains": "129608",
      "zone": "nu"
    },
    {
      "domains": "89753",
      "zone": "ee"
    },
    {
      "domains": "69796",
      "zone": "li"
    },
    {
      "domains": "62471",
      "zone": "pics"
    },
    {
      "domains": "44554",
      "zone": "mom"
    },
    {
      "domains": "32193",
      "zone": "tn"
    },
    {
      "domains": "13015",
      "zone": "gdn"
    },
    {
      "domains": "12561",
      "zone": "kg"
    },
    {
      "domains": "10457",
      "zone": "lk"
    },
    {
      "domains": "9784",
      "zone": "cy"
    },
    {
      "domains": "9099",
      "zone": "id"
    },
    {
      "domains": "4915",
      "zone": "game"
    },
    {
      "domains": "4832",
      "zone": "ruhr"
    },
    {
      "domains": "4778",
      "zone": "audio"
    },
    {
      "domains": "4256",
      "zone": "ax"
    },
    {
      "domains": "3704",
      "zone": "dz"
    },
    {
      "domains": "3565",
      "zone": "mc"
    },
    {
      "domains": "3324",
      "zone": "christmas"
    },
    {
      "domains": "3289",
      "zone": "ci"
    },
    {
      "domains": "2559",
      "zone": "hosting"
    },
    {
      "domains": "2215",
      "zone": "pr"
    },
    {
      "domains": "1852",
      "zone": "desi"
    },
    {
      "domains": "1398",
      "zone": "tz"
    },
    {
      "domains": "1350",
      "zone": "br"
    },
    {
      "domains": "1323",
      "zone": "bt"
    },
    {
      "domains": "1188",
      "zone": "diet"
    },
    {
      "domains": "1065",
      "zone": "flowers"
    },
    {
      "domains": "678",
      "zone": "guitars"
    },
    {
      "domains": "624",
      "zone": "xn--80ao21a"
    },
    {
      "domains": "582",
      "zone": "xn--pgbs0dh"
    },
    {
      "domains": "511",
      "zone": "lr"
    },
    {
      "domains": "497",
      "zone": "auto"
    },
    {
      "domains": "313",
      "zone": "car"
    },
    {
      "domains": "306",
      "zone": "xn--54b7fta0cc"
    },
    {
      "domains": "286",
      "zone": "cars"
    },
    {
      "domains": "151",
      "zone": "xn--l1acc"
    },
    {
      "domains": "92",
      "zone": "amazon"
    },
    {
      "domains": "50",
      "zone": "ve"
    },
    {
      "domains": "23",
      "zone": "arpa"
    },
    {
      "domains": "21",
      "zone": "wed"
    },
    {
      "domains": "14",
      "zone": "bd"
    },
    {
      "domains": "12",
      "zone": "gn"
    },
    {
      "domains": "7",
      "zone": "ieee"
    },
    {
      "domains": "7",
      "zone": "er"
    },
    {
      "domains": "6",
      "zone": "lb"
    }
  ],
  "total": "4861770"
}
