{
  "zones": [
    {
      "domains": "2528344",
      "zone": "ch"
    },
    {
      "domains": "1414923",
      "zone": "se"
    },
    {
      "domains": "214544",
      "zone": "lol"
    },
    {
      "domains": "171638",
      "zone": "kz"
    },
    {
      "domains": "128588",
      "zone": "nu"
    },
    {
      "domains": "90932",
      "zone": "ee"
    },
    {
      "domains": "70016",
      "zone": "li"
    },
    {
      "domains": "62200",
      "zone": "pics"
    },
    {
      "domains": "43680",
      "zone": "mom"
    },
    {
      "domains": "32723",
      "zone": "tn"
    },
    {
      "domains": "12756",
      "zone": "kg"
    },
    {
      "domains": "12652",
      "zone": "gdn"
    },
    {
      "domains": "10585",
      "zone": "lk"
    },
    {
      "domains": "9784",
      "zone": "cy"
    },
    {
      "domains": "8005",
      "zone": "id"
    },
    {
      "domains": "5334",
      "zone": "game"
    },
    {
      "domains": "4784",
      "zone": "audio"
    },
    {
      "domains": "4766",
      "zone": "ruhr"
    },
    {
      "domains": "4287",
      "zone": "ax"
    },
    {
      "domains": "4020",
      "zone": "ci"
    },
    {
      "domains": "3774",
      "zone": "dz"
    },
    {
      "domains": "3587",
      "zone": "mc"
    },
    {
      "domains": "3324",
      "zone": "christmas"
    },
    {
      "domains": "2538",
      "zone": "hosting"
    },
    {
      "domains": "2216",
      "zone": "pr"
    },
    {
      "domains": "1852",
      "zone": "desi"
    },
    {
      "domains": "1457",
      "zone": "tz"
    },
    {
      "domains": "1350",
      "zone": "br"
    },
    {
      "domains": "1348",
      "zone": "bt"
    },
    {
      "domains": "1194",
      "zone": "diet"
    },
    {
      "domains": "1052",
      "zone": "flowers"
    },
    {
      "domains": "669",
      "zone": "guitars"
    },
    {
      "domains": "584",
      "zone": "xn--pgbs0dh"
    },
    {
      "domains": "516",
      "zone": "lr"
    },
    {
      "domains": "514",
      "zone": "xn--80ao21a"
    },
    {
      "domains": "498",
      "zone": "auto"
    },
    {
      "domains": "309",
      "zone": "car"
    },
    {
      "domains": "306",
      "zone": "xn--54b7fta0cc"
    },
    {
      "domains": "280",
      "zone": "cars"
    },
    {
      "domains": "150",
      "zone": "xn--l1acc"
    },
    {
      "domains": "96",
      "zone": "amazon"
    },
    {
      "domains": "65",
      "zone": "ve"
    },
    {
      "domains": "26",
      "zone": "gn"
    },
    {
      "domains": "23",
      "zone": "arpa"
    },
    {
      "domains": "21",
      "zone": "wed"
    },
    {
      "domains": "14",
      "zone": "bd"
    },
    {
      "domains": "7",
      "zone": "ieee"
    },
    {
      "domains": "7",
      "zone": "er"
    },
    {
      "domains": "6",
      "zone": "lb"
    }
  ],
  "total": "4862344"
}
